MANIFEST.in
setup.py
pics2word/LogGen.py
pics2word/WriteHelp.py
pics2word/XtraFunctions.py
pics2word/__init__.py
pics2word/pics2word.py
pics2word.egg-info/PKG-INFO
pics2word.egg-info/SOURCES.txt
pics2word.egg-info/dependency_links.txt
pics2word.egg-info/entry_points.txt
pics2word.egg-info/requires.txt
pics2word.egg-info/top_level.txt
pics2word.egg-info/zip-safe