Metadata-Version: 1.2
Name: pics2word
Version: 0.9.6
Summary: A command line program to copy a large number of pictures into a word document.
Home-page: https://github.com/Ghostom998/pics2word.git
Author: Thomas Roberts
Author-email: tom_roberts.1992@hotmail.co.uk
License: GNU GPL V3.0
Platform: UNKNOWN
Classifier: Development Status :: 1 - Planning
Classifier: License :: OSI Approved :: GNU General Public License v3 (GPLv3)
Classifier: Programming Language :: Python :: 3.6
Classifier: Environment :: Console
Classifier: Topic :: Office/Business :: Office Suites
Requires-Python: >=3.6.4
